napari_features_selector/__init__.py
napari_features_selector/_ga_feature_selection.py
napari_features_selector/_version.py
napari_features_selector/_widget.py
napari_features_selector/napari.yaml
napari_features_selector/_tests/__init__.py
napari_features_selector/_tests/iris_dataset.csv
napari_features_selector/_tests/testGA.csv
napari_features_selector/_tests/test_ga_feature_selection.py
napari_features_selector/_tests/test_widget.py
napari_features_selector-0.0.4.dist-info/LICENSE
napari_features_selector-0.0.4.dist-info/METADATA
napari_features_selector-0.0.4.dist-info/WHEEL
napari_features_selector-0.0.4.dist-info/entry_points.txt
napari_features_selector-0.0.4.dist-info/top_level.txt
napari_features_selector-0.0.4.dist-info/RECORD
