Metadata-Version: 2.1
Name: napari-features-selector
Version: 0.0.4
Summary: A lightweight widget for features selection.
Home-page: https://github.com/kumar-sanjeeev/napari-features-selector
Author: Sanjeev Kumar
Author-email: kumar.san96@gmail.com
License: BSD-3-Clause
Project-URL: Bug Tracker, https://github.com/kumar-sanjeeev/napari-features-selector/issues
Project-URL: Documentation, https://github.com/kumar-sanjeeev/napari-features-selector#README.md
Project-URL: Source Code, https://github.com/kumar-sanjeeev/napari-features-selector
Project-URL: User Support, https://github.com/kumar-sanjeeev/napari-features-selector/issues
Classifier: Development Status :: 2 - Pre-Alpha
Classifier: Framework :: napari
Classifier: Intended Audience :: Developers
Classifier: License :: OSI Approved :: BSD License
Classifier: Operating System :: OS Independent
Classifier: Programming Language :: Python
Classifier: Programming Language :: Python :: 3
Classifier: Programming Language :: Python :: 3 :: Only
Classifier: Programming Language :: Python :: 3.8
Classifier: Programming Language :: Python :: 3.9
Classifier: Programming Language :: Python :: 3.10
Classifier: Topic :: Scientific/Engineering :: Image Processing
Requires-Python: >=3.8
License-File: LICENSE
Requires-Dist: numpy
Requires-Dist: magicgui
Requires-Dist: qtpy
Requires-Dist: pandas
Requires-Dist: scikit-learn
Requires-Dist: sklearn-genetic-opt
Provides-Extra: testing
Requires-Dist: tox ; extra == 'testing'
Requires-Dist: pytest ; extra == 'testing'
Requires-Dist: pytest-cov ; extra == 'testing'
Requires-Dist: pytest-qt ; extra == 'testing'
Requires-Dist: napari ; extra == 'testing'
Requires-Dist: pyqt5 ; extra == 'testing'
